pmn/__init__.py
pmn/abstract_process_view.py
pmn/application.py
pmn/default_config.py
pmn/info_format.py
pmn/list_process_view.py
pmn/pmn.py
pmn/process_tree.py
pmn/search_view.py
pmn/size.py
pmn/status_view.py
pmn/string_format.py
pmn/tree_process_view.py
pmn-0.1.data/scripts/pmn
pmn-0.1.dist-info/METADATA
pmn-0.1.dist-info/WHEEL
pmn-0.1.dist-info/top_level.txt
pmn-0.1.dist-info/RECORD
