Metadata-Version: 2.1
Name: pmn
Version: 0.1
Summary: terminal process manager for Linux
Home-page: https://github.com/ivanjermakov/pmn
Author: Ivan Ermakov
Author-email: ivanjermakov1@gmail.com
License: MIT
Platform: UNKNOWN
Requires-Python: >=3
Requires-Dist: anytree
Requires-Dist: psutil
Requires-Dist: click
